<?xml version="1.0" encoding="ISO-8859-1" ?>
<objects>
  <Location>
    <streetName>Thomas Poulsens Allé</streetName>
    <streetBuildingIdentifier>10</streetBuildingIdentifier>
    <postCodeIdentifier>7430</postCodeIdentifier>
    <districtName>Ikast</districtName>
    <districtSubDivisionIdentifier></districtSubDivisionIdentifier>
    <latitude>56.13701775</latitude>
    <longitude>9.14567086</longitude>
  </Location>
  <Location>
    <streetName>Nørregade</streetName>
    <streetBuildingIdentifier>43C</streetBuildingIdentifier>
    <postCodeIdentifier>3300</postCodeIdentifier>
    <districtName>Frederiksværk</districtName>
    <districtSubDivisionIdentifier></districtSubDivisionIdentifier>
    <latitude>55.97888963</latitude>
    <longitude>12.01913661</longitude>
  </Location>
  <Location>
    <streetName>Slotsgade</streetName>
    <streetBuildingIdentifier>22</streetBuildingIdentifier>
    <postCodeIdentifier>5000</postCodeIdentifier>
    <districtName>Odense C</districtName>
    <districtSubDivisionIdentifier></districtSubDivisionIdentifier>
    <latitude>55.39648052</latitude>
    <longitude>10.38300058</longitude>
  </Location>
  <Location>
    <streetName>Vejlevej</streetName>
    <streetBuildingIdentifier>114</streetBuildingIdentifier>
    <postCodeIdentifier>6000</postCodeIdentifier>
    <districtName>Kolding</districtName>
    <districtSubDivisionIdentifier></districtSubDivisionIdentifier>
    <latitude>55.50311043</latitude>
    <longitude>9.45884308</longitude>
  </Location>
  <Location>
    <streetName>K. Christensens Vej</streetName>
    <streetBuildingIdentifier>1</streetBuildingIdentifier>
    <postCodeIdentifier>9200</postCodeIdentifier>
    <districtName>Aalborg</districtName>
    <districtSubDivisionIdentifier></districtSubDivisionIdentifier>
    <latitude>57.01355137</latitude>
    <longitude>9.89569682</longitude>
  </Location>
  <Location>
    <streetName>Cikorievej</streetName>
    <streetBuildingIdentifier>2a</streetBuildingIdentifier>
    <postCodeIdentifier>5220</postCodeIdentifier>
    <districtName>Odense SØ</districtName>
    <districtSubDivisionIdentifier></districtSubDivisionIdentifier>
    <latitude>55.392824</latitude>
    <longitude>10.43590815</longitude>
  </Location>
  <Location>
    <streetName>Østerbakken</streetName>
    <streetBuildingIdentifier>71</streetBuildingIdentifier>
    <postCodeIdentifier>7700</postCodeIdentifier>
    <districtName>Thisted</districtName>
    <districtSubDivisionIdentifier></districtSubDivisionIdentifier>
    <latitude>56.9589005</latitude>
    <longitude>8.71127058</longitude>
  </Location>
  <Location>
    <streetName>Apotekervej</streetName>
    <streetBuildingIdentifier>21</streetBuildingIdentifier>
    <postCodeIdentifier>4180</postCodeIdentifier>
    <districtName>Sorø</districtName>
    <districtSubDivisionIdentifier></districtSubDivisionIdentifier>
    <latitude>55.44557212</latitude>
    <longitude>11.56340752</longitude>
  </Location>
  <Location>
    <streetName>Sadelmagerporten</streetName>
    <streetBuildingIdentifier>2</streetBuildingIdentifier>
    <postCodeIdentifier>2650</postCodeIdentifier>
    <districtName>Hvidovre</districtName>
    <districtSubDivisionIdentifier></districtSubDivisionIdentifier>
    <latitude>55.62732347</latitude>
    <longitude>12.45425379</longitude>
  </Location>
  <Location>
    <streetName>Marienbergvej</streetName>
    <streetBuildingIdentifier>104</streetBuildingIdentifier>
    <postCodeIdentifier>4760</postCodeIdentifier>
    <districtName>Vordingborg</districtName>
    <districtSubDivisionIdentifier></districtSubDivisionIdentifier>
    <latitude>54.99932535</latitude>
    <longitude>11.89326272</longitude>
  </Location>
  <Location>
    <streetName>Østerbrogade</streetName>
    <streetBuildingIdentifier>43</streetBuildingIdentifier>
    <postCodeIdentifier>8500</postCodeIdentifier>
    <districtName>Grenaa</districtName>
    <districtSubDivisionIdentifier></districtSubDivisionIdentifier>
    <latitude>56.41416954</latitude>
    <longitude>10.88678578</longitude>
  </Location>
  <Location>
    <streetName>Odinsvej</streetName>
    <streetBuildingIdentifier>2</streetBuildingIdentifier>
    <postCodeIdentifier>4100</postCodeIdentifier>
    <districtName>Ringsted</districtName>
    <districtSubDivisionIdentifier></districtSubDivisionIdentifier>
    <latitude>55.43519947</latitude>
    <longitude>11.79242777</longitude>
  </Location>
  <Location>
    <streetName>Thorslundsvej</streetName>
    <streetBuildingIdentifier>1A</streetBuildingIdentifier>
    <postCodeIdentifier>5000</postCodeIdentifier>
    <districtName>Odense C</districtName>
    <districtSubDivisionIdentifier></districtSubDivisionIdentifier>
    <latitude>55.41457435</latitude>
    <longitude>10.36750337</longitude>
  </Location>
  <Location>
    <streetName>Hjørringvej</streetName>
    <streetBuildingIdentifier>125</streetBuildingIdentifier>
    <postCodeIdentifier>9900</postCodeIdentifier>
    <districtName>Frederikshavn</districtName>
    <districtSubDivisionIdentifier></districtSubDivisionIdentifier>
    <latitude>57.44677268</latitude>
    <longitude>10.51226891</longitude>
  </Location>
  <Location>
    <streetName>Vesterbrogade</streetName>
    <streetBuildingIdentifier>25</streetBuildingIdentifier>
    <postCodeIdentifier>1620</postCodeIdentifier>
    <districtName>København V</districtName>
    <districtSubDivisionIdentifier></districtSubDivisionIdentifier>
    <latitude>55.67290077</latitude>
    <longitude>12.55925849</longitude>
  </Location>
  <Location>
    <streetName>Marsvej</streetName>
    <streetBuildingIdentifier>4</streetBuildingIdentifier>
    <postCodeIdentifier>8960</postCodeIdentifier>
    <districtName>Randers SØ</districtName>
    <districtSubDivisionIdentifier></districtSubDivisionIdentifier>
    <latitude>56.42745862</latitude>
    <longitude>10.05988818</longitude>
  </Location>
  <Location>
    <streetName>Brovejen</streetName>
    <streetBuildingIdentifier>34</streetBuildingIdentifier>
    <postCodeIdentifier>4930</postCodeIdentifier>
    <districtName>Maribo</districtName>
    <districtSubDivisionIdentifier></districtSubDivisionIdentifier>
    <latitude>54.77639111</latitude>
    <longitude>11.48630843</longitude>
  </Location>
  <Location>
    <streetName>Vestergade</streetName>
    <streetBuildingIdentifier>54</streetBuildingIdentifier>
    <postCodeIdentifier>7200</postCodeIdentifier>
    <districtName>Grindsted</districtName>
    <districtSubDivisionIdentifier></districtSubDivisionIdentifier>
    <latitude>55.75941916</latitude>
    <longitude>8.92021313</longitude>
  </Location>
  <Location>
    <streetName>Bystævnevej</streetName>
    <streetBuildingIdentifier>3</streetBuildingIdentifier>
    <postCodeIdentifier>5200</postCodeIdentifier>
    <districtName>Odense V</districtName>
    <districtSubDivisionIdentifier></districtSubDivisionIdentifier>
    <latitude>55.39428657</latitude>
    <longitude>10.34687662</longitude>
  </Location>
  <Location>
    <streetName>Åstrupvej</streetName>
    <streetBuildingIdentifier>2</streetBuildingIdentifier>
    <postCodeIdentifier>9800</postCodeIdentifier>
    <districtName>Hjørring</districtName>
    <districtSubDivisionIdentifier></districtSubDivisionIdentifier>
    <latitude>57.45633461</latitude>
    <longitude>9.9779977</longitude>
  </Location>
  <Location>
    <streetName>Viborgvej</streetName>
    <streetBuildingIdentifier>71</streetBuildingIdentifier>
    <postCodeIdentifier>7400</postCodeIdentifier>
    <districtName>Herning</districtName>
    <districtSubDivisionIdentifier></districtSubDivisionIdentifier>
    <latitude>56.14484822</latitude>
    <longitude>8.99237137</longitude>
  </Location>
  <Location>
    <streetName>Motalavej</streetName>
    <streetBuildingIdentifier>141</streetBuildingIdentifier>
    <postCodeIdentifier>4220</postCodeIdentifier>
    <districtName>Korsør</districtName>
    <districtSubDivisionIdentifier></districtSubDivisionIdentifier>
    <latitude>55.34968154</latitude>
    <longitude>11.13964639</longitude>
  </Location>
  <Location>
    <streetName>Jomfrustien</streetName>
    <streetBuildingIdentifier>44</streetBuildingIdentifier>
    <postCodeIdentifier>6100</postCodeIdentifier>
    <districtName>Haderslev</districtName>
    <districtSubDivisionIdentifier></districtSubDivisionIdentifier>
    <latitude>55.25058155</latitude>
    <longitude>9.49912715</longitude>
  </Location>
  <Location>
    <streetName>Bondovej</streetName>
    <streetBuildingIdentifier>5</streetBuildingIdentifier>
    <postCodeIdentifier>5250</postCodeIdentifier>
    <districtName>Odense SV</districtName>
    <districtSubDivisionIdentifier></districtSubDivisionIdentifier>
    <latitude>55.36318408</latitude>
    <longitude>10.35007994</longitude>
  </Location>
  <Location>
    <streetName>Vejlevej</streetName>
    <streetBuildingIdentifier>54</streetBuildingIdentifier>
    <postCodeIdentifier>8700</postCodeIdentifier>
    <districtName>Horsens</districtName>
    <districtSubDivisionIdentifier></districtSubDivisionIdentifier>
    <latitude>55.84688962</latitude>
    <longitude>9.82392955</longitude>
  </Location>
  <Location>
    <streetName>Ølbycenter</streetName>
    <streetBuildingIdentifier>4</streetBuildingIdentifier>
    <postCodeIdentifier>4600</postCodeIdentifier>
    <districtName>Køge</districtName>
    <districtSubDivisionIdentifier></districtSubDivisionIdentifier>
    <latitude>55.47941508</latitude>
    <longitude>12.17483268</longitude>
  </Location>
  <Location>
    <streetName>Industrivej</streetName>
    <streetBuildingIdentifier>3</streetBuildingIdentifier>
    <postCodeIdentifier>7600</postCodeIdentifier>
    <districtName>Struer</districtName>
    <districtSubDivisionIdentifier></districtSubDivisionIdentifier>
    <latitude>56.48682561</latitude>
    <longitude>8.58305556</longitude>
  </Location>
  <Location>
    <streetName>Grønlandsvej</streetName>
    <streetBuildingIdentifier>3A</streetBuildingIdentifier>
    <postCodeIdentifier>8700</postCodeIdentifier>
    <districtName>Horsens</districtName>
    <districtSubDivisionIdentifier></districtSubDivisionIdentifier>
    <latitude>55.85581789</latitude>
    <longitude>9.86395437</longitude>
  </Location>
  <Location>
    <streetName>Christian X&apos;s Vej</streetName>
    <streetBuildingIdentifier>112</streetBuildingIdentifier>
    <postCodeIdentifier>8260</postCodeIdentifier>
    <districtName>Viby J</districtName>
    <districtSubDivisionIdentifier></districtSubDivisionIdentifier>
    <latitude>56.12196487</latitude>
    <longitude>10.16933306</longitude>
  </Location>
  <Location>
    <streetName>Stationsalleen</streetName>
    <streetBuildingIdentifier>7</streetBuildingIdentifier>
    <postCodeIdentifier>2730</postCodeIdentifier>
    <districtName>Herlev</districtName>
    <districtSubDivisionIdentifier></districtSubDivisionIdentifier>
    <latitude>55.71842593</latitude>
    <longitude>12.44619492</longitude>
  </Location>
  <Location>
    <streetName>Viborgvej</streetName>
    <streetBuildingIdentifier>165</streetBuildingIdentifier>
    <postCodeIdentifier>8210</postCodeIdentifier>
    <districtName>Århus V</districtName>
    <districtSubDivisionIdentifier>Hasle</districtSubDivisionIdentifier>
    <latitude>56.1688579</latitude>
    <longitude>10.16098177</longitude>
  </Location>
  <Location>
    <streetName>Storebæltsvej</streetName>
    <streetBuildingIdentifier>5</streetBuildingIdentifier>
    <postCodeIdentifier>5800</postCodeIdentifier>
    <districtName>Nyborg</districtName>
    <districtSubDivisionIdentifier></districtSubDivisionIdentifier>
    <latitude>55.30933307</latitude>
    <longitude>10.80707138</longitude>
  </Location>
  <Location>
    <streetName>Vardevej</streetName>
    <streetBuildingIdentifier>87</streetBuildingIdentifier>
    <postCodeIdentifier>6900</postCodeIdentifier>
    <districtName>Skjern</districtName>
    <districtSubDivisionIdentifier></districtSubDivisionIdentifier>
    <latitude>55.93537095</latitude>
    <longitude>8.50555105</longitude>
  </Location>
  <Location>
    <streetName>Grønnegade</streetName>
    <streetBuildingIdentifier>10.12.10</streetBuildingIdentifier>
    <postCodeIdentifier>7900</postCodeIdentifier>
    <districtName>Nykøbing Mors</districtName>
    <districtSubDivisionIdentifier></districtSubDivisionIdentifier>
    <latitude>56.79567825</latitude>
    <longitude>8.85787958</longitude>
  </Location>
  <Location>
    <streetName>Grønlandsgade</streetName>
    <streetBuildingIdentifier>6</streetBuildingIdentifier>
    <postCodeIdentifier>4690</postCodeIdentifier>
    <districtName>Haslev</districtName>
    <districtSubDivisionIdentifier></districtSubDivisionIdentifier>
    <latitude>55.33007092</latitude>
    <longitude>11.9404003</longitude>
  </Location>
  <Location>
    <streetName>Sæbygårdvej</streetName>
    <streetBuildingIdentifier>29</streetBuildingIdentifier>
    <postCodeIdentifier>9300</postCodeIdentifier>
    <districtName>Sæby</districtName>
    <districtSubDivisionIdentifier></districtSubDivisionIdentifier>
    <latitude>57.33368558</latitude>
    <longitude>10.50348202</longitude>
  </Location>
  <Location>
    <streetName>Østervangsvej</streetName>
    <streetBuildingIdentifier>2</streetBuildingIdentifier>
    <postCodeIdentifier>6715</postCodeIdentifier>
    <districtName>Esbjerg N</districtName>
    <districtSubDivisionIdentifier></districtSubDivisionIdentifier>
    <latitude>55.50199583</latitude>
    <longitude>8.45352854</longitude>
  </Location>
  <Location>
    <streetName>Vejlegadebro</streetName>
    <streetBuildingIdentifier>6</streetBuildingIdentifier>
    <postCodeIdentifier>4900</postCodeIdentifier>
    <districtName>Nakskov</districtName>
    <districtSubDivisionIdentifier></districtSubDivisionIdentifier>
    <latitude>54.83387481</latitude>
    <longitude>11.13123403</longitude>
  </Location>
  <Location>
    <streetName>Strandvejen</streetName>
    <streetBuildingIdentifier>1</streetBuildingIdentifier>
    <postCodeIdentifier>4200</postCodeIdentifier>
    <districtName>Slagelse</districtName>
    <districtSubDivisionIdentifier></districtSubDivisionIdentifier>
    <latitude>55.39951019</latitude>
    <longitude>11.33752364</longitude>
  </Location>
  <Location>
    <streetName>Amagerbrogade</streetName>
    <streetBuildingIdentifier>114</streetBuildingIdentifier>
    <postCodeIdentifier>2300</postCodeIdentifier>
    <districtName>København S</districtName>
    <districtSubDivisionIdentifier></districtSubDivisionIdentifier>
    <latitude>55.65856562</latitude>
    <longitude>12.60702418</longitude>
  </Location>
  <Location>
    <streetName>Frederik d. 7&apos;s Gade</streetName>
    <streetBuildingIdentifier>38</streetBuildingIdentifier>
    <postCodeIdentifier>6600</postCodeIdentifier>
    <districtName>Vejen</districtName>
    <districtSubDivisionIdentifier></districtSubDivisionIdentifier>
    <latitude>55.48306222</latitude>
    <longitude>9.14665093</longitude>
  </Location>
  <Location>
    <streetName>Langebro</streetName>
    <streetBuildingIdentifier>44</streetBuildingIdentifier>
    <postCodeIdentifier>6200</postCodeIdentifier>
    <districtName>Aabenraa</districtName>
    <districtSubDivisionIdentifier></districtSubDivisionIdentifier>
    <latitude>55.03575216</latitude>
    <longitude>9.41606005</longitude>
  </Location>
  <Location>
    <streetName>Tåstrup Møllevej</streetName>
    <streetBuildingIdentifier>1</streetBuildingIdentifier>
    <postCodeIdentifier>4300</postCodeIdentifier>
    <districtName>Holbæk</districtName>
    <districtSubDivisionIdentifier></districtSubDivisionIdentifier>
    <latitude>55.70443667</latitude>
    <longitude>11.70719441</longitude>
  </Location>
  <Location>
    <streetName>Brovejen</streetName>
    <streetBuildingIdentifier>14</streetBuildingIdentifier>
    <postCodeIdentifier>5500</postCodeIdentifier>
    <districtName>Middelfart</districtName>
    <districtSubDivisionIdentifier></districtSubDivisionIdentifier>
    <latitude>55.49855287</latitude>
    <longitude>9.75914648</longitude>
  </Location>
  <Location>
    <streetName>Skaadsmosevej</streetName>
    <streetBuildingIdentifier>2</streetBuildingIdentifier>
    <postCodeIdentifier>6950</postCodeIdentifier>
    <districtName>Ringkøbing</districtName>
    <districtSubDivisionIdentifier></districtSubDivisionIdentifier>
    <latitude>56.08626005</latitude>
    <longitude>8.27814088</longitude>
  </Location>
  <Location>
    <streetName>Lygten</streetName>
    <streetBuildingIdentifier>49</streetBuildingIdentifier>
    <postCodeIdentifier>2400</postCodeIdentifier>
    <districtName>København NV</districtName>
    <districtSubDivisionIdentifier></districtSubDivisionIdentifier>
    <latitude>55.70651858</latitude>
    <longitude>12.53820746</longitude>
  </Location>
  <Location>
    <streetName>Jernbanegade</streetName>
    <streetBuildingIdentifier>29</streetBuildingIdentifier>
    <postCodeIdentifier>8900</postCodeIdentifier>
    <districtName>Randers</districtName>
    <districtSubDivisionIdentifier></districtSubDivisionIdentifier>
    <latitude>56.46198995</latitude>
    <longitude>10.02207857</longitude>
  </Location>
  <Location>
    <streetName>Amager Landevej</streetName>
    <streetBuildingIdentifier>42</streetBuildingIdentifier>
    <postCodeIdentifier>2770</postCodeIdentifier>
    <districtName>Kastrup</districtName>
    <districtSubDivisionIdentifier>Tårnby</districtSubDivisionIdentifier>
    <latitude>55.63678487</latitude>
    <longitude>12.6186914</longitude>
  </Location>
  <Location>
    <streetName>Storegade</streetName>
    <streetBuildingIdentifier>227</streetBuildingIdentifier>
    <postCodeIdentifier>6700</postCodeIdentifier>
    <districtName>Esbjerg</districtName>
    <districtSubDivisionIdentifier></districtSubDivisionIdentifier>
    <latitude>55.47905422</latitude>
    <longitude>8.49517307</longitude>
  </Location>
  <Location>
    <streetName>Ravnsøvej</streetName>
    <streetBuildingIdentifier>60</streetBuildingIdentifier>
    <postCodeIdentifier>8240</postCodeIdentifier>
    <districtName>Risskov</districtName>
    <districtSubDivisionIdentifier></districtSubDivisionIdentifier>
    <latitude>56.20175699</latitude>
    <longitude>10.24557038</longitude>
  </Location>
  <Location>
    <streetName>Sorøvej</streetName>
    <streetBuildingIdentifier>2</streetBuildingIdentifier>
    <postCodeIdentifier>4200</postCodeIdentifier>
    <districtName>Slagelse</districtName>
    <districtSubDivisionIdentifier></districtSubDivisionIdentifier>
    <latitude>55.40758644</latitude>
    <longitude>11.36997559</longitude>
  </Location>
  <Location>
    <streetName>Marsk Stigs Vej</streetName>
    <streetBuildingIdentifier>1</streetBuildingIdentifier>
    <postCodeIdentifier>8800</postCodeIdentifier>
    <districtName>Viborg</districtName>
    <districtSubDivisionIdentifier></districtSubDivisionIdentifier>
    <latitude>56.44468405</latitude>
    <longitude>9.3909027</longitude>
  </Location>
  <Location>
    <streetName>Banegårdsgade</streetName>
    <streetBuildingIdentifier>30</streetBuildingIdentifier>
    <postCodeIdentifier>8300</postCodeIdentifier>
    <districtName>Odder</districtName>
    <districtSubDivisionIdentifier></districtSubDivisionIdentifier>
    <latitude>55.96820037</latitude>
    <longitude>10.14865304</longitude>
  </Location>
  <Location>
    <streetName>Finsensvej</streetName>
    <streetBuildingIdentifier>78</streetBuildingIdentifier>
    <postCodeIdentifier>2000</postCodeIdentifier>
    <districtName>Frederiksberg</districtName>
    <districtSubDivisionIdentifier></districtSubDivisionIdentifier>
    <latitude>55.68228129</latitude>
    <longitude>12.50487141</longitude>
  </Location>
  <Location>
    <streetName>Mølmarksvej</streetName>
    <streetBuildingIdentifier>185</streetBuildingIdentifier>
    <postCodeIdentifier>5700</postCodeIdentifier>
    <districtName>Svendborg</districtName>
    <districtSubDivisionIdentifier></districtSubDivisionIdentifier>
    <latitude>55.0632777</latitude>
    <longitude>10.59060511</longitude>
  </Location>
  <Location>
    <streetName>Marius Jensensvej</streetName>
    <streetBuildingIdentifier>1b</streetBuildingIdentifier>
    <postCodeIdentifier>7800</postCodeIdentifier>
    <districtName>Skive</districtName>
    <districtSubDivisionIdentifier></districtSubDivisionIdentifier>
    <latitude>56.56267454</latitude>
    <longitude>9.03029679</longitude>
  </Location>
  <Location>
    <streetName>A. C. Hansensvej</streetName>
    <streetBuildingIdentifier>2</streetBuildingIdentifier>
    <postCodeIdentifier>3600</postCodeIdentifier>
    <districtName>Frederikssund</districtName>
    <districtSubDivisionIdentifier></districtSubDivisionIdentifier>
    <latitude>55.83531749</latitude>
    <longitude>12.06299326</longitude>
  </Location>
  <Location>
    <streetName>Mosevej</streetName>
    <streetBuildingIdentifier>1A</streetBuildingIdentifier>
    <postCodeIdentifier>6000</postCodeIdentifier>
    <districtName>Kolding</districtName>
    <districtSubDivisionIdentifier></districtSubDivisionIdentifier>
    <latitude>55.47164576</latitude>
    <longitude>9.46974065</longitude>
  </Location>
  <Location>
    <streetName>Industriskellet</streetName>
    <streetBuildingIdentifier>1</streetBuildingIdentifier>
    <postCodeIdentifier>2635</postCodeIdentifier>
    <districtName>Ishøj</districtName>
    <districtSubDivisionIdentifier></districtSubDivisionIdentifier>
    <latitude>55.6075714</latitude>
    <longitude>12.35583213</longitude>
  </Location>
  <Location>
    <streetName>Erantisvej</streetName>
    <streetBuildingIdentifier>44-46</streetBuildingIdentifier>
    <postCodeIdentifier>4700</postCodeIdentifier>
    <districtName>Næstved</districtName>
    <districtSubDivisionIdentifier></districtSubDivisionIdentifier>
    <latitude>55.23787463</latitude>
    <longitude>11.77791304</longitude>
  </Location>
  <Location>
    <streetName>Skejbyvej</streetName>
    <streetBuildingIdentifier>499</streetBuildingIdentifier>
    <postCodeIdentifier>8200</postCodeIdentifier>
    <districtName>Århus N</districtName>
    <districtSubDivisionIdentifier></districtSubDivisionIdentifier>
    <latitude>56.20000984</latitude>
    <longitude>10.18282842</longitude>
  </Location>
  <Location>
    <streetName>Herningvej</streetName>
    <streetBuildingIdentifier>36</streetBuildingIdentifier>
    <postCodeIdentifier>7500</postCodeIdentifier>
    <districtName>Holstebro</districtName>
    <districtSubDivisionIdentifier></districtSubDivisionIdentifier>
    <latitude>56.35014029</latitude>
    <longitude>8.62346244</longitude>
  </Location>
  <Location>
    <streetName>Centrumgaden</streetName>
    <streetBuildingIdentifier>16</streetBuildingIdentifier>
    <postCodeIdentifier>2750</postCodeIdentifier>
    <districtName>Ballerup</districtName>
    <districtSubDivisionIdentifier></districtSubDivisionIdentifier>
    <latitude>55.7308222</latitude>
    <longitude>12.36036973</longitude>
  </Location>
  <Location>
    <streetName>Banegårdspladsen</streetName>
    <streetBuildingIdentifier>10</streetBuildingIdentifier>
    <postCodeIdentifier>5600</postCodeIdentifier>
    <districtName>Faaborg</districtName>
    <districtSubDivisionIdentifier></districtSubDivisionIdentifier>
    <latitude>55.09375842</latitude>
    <longitude>10.25042434</longitude>
  </Location>
  <Location>
    <streetName>Elmegade</streetName>
    <streetBuildingIdentifier>22</streetBuildingIdentifier>
    <postCodeIdentifier>4400</postCodeIdentifier>
    <districtName>Kalundborg</districtName>
    <districtSubDivisionIdentifier></districtSubDivisionIdentifier>
    <latitude>55.67849818</latitude>
    <longitude>11.09887323</longitude>
  </Location>
  <Location>
    <streetName>Bygmestervej</streetName>
    <streetBuildingIdentifier>1</streetBuildingIdentifier>
    <postCodeIdentifier>5750</postCodeIdentifier>
    <districtName>Ringe</districtName>
    <districtSubDivisionIdentifier></districtSubDivisionIdentifier>
    <latitude>55.23678971</latitude>
    <longitude>10.48939843</longitude>
  </Location>
  <Location>
    <streetName>Vestre Landevej</streetName>
    <streetBuildingIdentifier>71</streetBuildingIdentifier>
    <postCodeIdentifier>6800</postCodeIdentifier>
    <districtName>Varde</districtName>
    <districtSubDivisionIdentifier></districtSubDivisionIdentifier>
    <latitude>55.62552733</latitude>
    <longitude>8.46267367</longitude>
  </Location>
  <Location>
    <streetName>Østergade</streetName>
    <streetBuildingIdentifier>52</streetBuildingIdentifier>
    <postCodeIdentifier>9700</postCodeIdentifier>
    <districtName>Brønderslev</districtName>
    <districtSubDivisionIdentifier></districtSubDivisionIdentifier>
    <latitude>57.26367941</latitude>
    <longitude>9.950371</longitude>
  </Location>
  <Location>
    <streetName>Banegårdsvej</streetName>
    <streetBuildingIdentifier>13</streetBuildingIdentifier>
    <postCodeIdentifier>2600</postCodeIdentifier>
    <districtName>Glostrup</districtName>
    <districtSubDivisionIdentifier></districtSubDivisionIdentifier>
    <latitude>55.66436095</latitude>
    <longitude>12.40079539</longitude>
  </Location>
  <Location>
    <streetName>Alsgade</streetName>
    <streetBuildingIdentifier>93-95</streetBuildingIdentifier>
    <postCodeIdentifier>6400</postCodeIdentifier>
    <districtName>Sønderborg</districtName>
    <districtSubDivisionIdentifier></districtSubDivisionIdentifier>
    <latitude>54.9192854</latitude>
    <longitude>9.80736504</longitude>
  </Location>
  <Location>
    <streetName>Hostrupvej</streetName>
    <streetBuildingIdentifier>68</streetBuildingIdentifier>
    <postCodeIdentifier>9500</postCodeIdentifier>
    <districtName>Hobro</districtName>
    <districtSubDivisionIdentifier></districtSubDivisionIdentifier>
    <latitude>56.64550365</latitude>
    <longitude>9.79405081</longitude>
  </Location>
  <Location>
    <streetName>Birkedalsvej</streetName>
    <streetBuildingIdentifier>23</streetBuildingIdentifier>
    <postCodeIdentifier>3000</postCodeIdentifier>
    <districtName>Helsingør</districtName>
    <districtSubDivisionIdentifier></districtSubDivisionIdentifier>
    <latitude>56.01990894</latitude>
    <longitude>12.57121041</longitude>
  </Location>
  <Location>
    <streetName>Vejlevej</streetName>
    <streetBuildingIdentifier>38</streetBuildingIdentifier>
    <postCodeIdentifier>7000</postCodeIdentifier>
    <districtName>Fredericia</districtName>
    <districtSubDivisionIdentifier></districtSubDivisionIdentifier>
    <latitude>55.56960752</latitude>
    <longitude>9.7184118</longitude>
  </Location>
  <Location>
    <streetName>Fejøvej</streetName>
    <streetBuildingIdentifier>1</streetBuildingIdentifier>
    <postCodeIdentifier>4700</postCodeIdentifier>
    <districtName>Næstved</districtName>
    <districtSubDivisionIdentifier></districtSubDivisionIdentifier>
    <latitude>55.22119141</latitude>
    <longitude>11.75684112</longitude>
  </Location>
  <Location>
    <streetName>Hundige Storcenter</streetName>
    <streetBuildingIdentifier>25</streetBuildingIdentifier>
    <postCodeIdentifier>2670</postCodeIdentifier>
    <districtName>Greve</districtName>
    <districtSubDivisionIdentifier></districtSubDivisionIdentifier>
    <latitude>55.6046299</latitude>
    <longitude>12.33348878</longitude>
  </Location>
  <Location>
    <streetName>Tømmergade</streetName>
    <streetBuildingIdentifier>12</streetBuildingIdentifier>
    <postCodeIdentifier>4800</postCodeIdentifier>
    <districtName>Nykøbing F</districtName>
    <districtSubDivisionIdentifier></districtSubDivisionIdentifier>
    <latitude>54.76888181</latitude>
    <longitude>11.86448494</longitude>
  </Location>
  <Location>
    <streetName>Nørrevænget</streetName>
    <streetBuildingIdentifier>49</streetBuildingIdentifier>
    <postCodeIdentifier>8600</postCodeIdentifier>
    <districtName>Silkeborg</districtName>
    <districtSubDivisionIdentifier></districtSubDivisionIdentifier>
    <latitude>56.18587395</latitude>
    <longitude>9.54740147</longitude>
  </Location>
</objects>
